{
  "info": {
    "title": "Example ODM model for the ZCL Level cluster", 
    "version": "20190504", 
    "copyright": "no copyright", 
    "license": "not licensed"
  }, 
  "namespace": {
    "zcl": "http://example.com/zcl/odm"
  }, 
  "defaultNamespace": "zcl", 
  "odmObject": {
    "Level": {
      "name": "Level Control", 
      "odmRequired": [
        "#/odmObject/Level/odmProperty/CurrentLevel", 
        "#/odmObject/Level/odmAction/MoveToLevel", 
        "#/odmObject/Level/odmAction/Move", 
        "#/odmObject/Level/odmAction/Stop", 
        "#/odmObject/Level/odmAction/MoveToLevelwithOnOff", 
        "#/odmObject/Level/odmAction/MovewithOnOff", 
        "#/odmObject/Level/odmAction/StepwithOnOff", 
        "#/odmObject/Level/odmAction/StopwithOnOff"
      ],
      "odmProperty": {
        "CurrentLevel": {
          "name": "Current Level", 
          "type": "number", 
          "widthInBits": 8, 
          "minimum": 0, 
          "maximum": 254
        }, 
        "RemainingTime": {
          "odmRef": "#/odmData/TransitionTimeData", 
          "name": "Remaining Time", 
          "default": 0
        }, 
        "OnOffTransitionTime": {
          "odmRef": "#/odmData/TransitionTimeData", 
          "name": "On Off Transition Time", 
          "default": 0
        }, 
        "OnLevel": {
          "name": "On Level", 
          "type": "number", 
          "widthInBits": 8, 
          "minimum": 0, 
          "maximum": 255, 
          "default": 255
        }, 
        "OnTransitionTime": {
          "odmRef": "#/odmData/TransitionTimeData", 
          "name": "On Transition Time"
        }, 
        "OffTransitionTime": {
          "odmRef": "#/odmData/TransitionTimeData", 
          "name": "Off Transition Time", 
          "id": 19
        }, 
        "DefaultMoveRate": {
          "name": "Default Move Rate", 
          "id": 20, 
          "type": "number", 
          "widthInBits": 16, 
          "minimum": 0, 
          "maximum": 254
        }
      }, 
      "odmAction": {
        "MoveToLevel": {
          "name": "Move to Level", 
          "odmRequired": [
            "#/odmObject/Level/odmAction/MoveToLevel/odmData/level", 
            "#/odmObject/Level/odmAction/MoveToLevel/odmData/transitiontime"
          ],
          "odmInputData": [
            "#/odmObject/Level/odmAction/MoveToLevel/odmData/level", 
            "#/odmObject/Level/odmAction/MoveToLevel/odmData/transitiontime"
          ],
          "odmData": {
            "level": {
              "name": "Level", 
              "type": "number", 
              "widthInBits": 8, 
              "minimum": 0, 
              "maximum": 254
            }, 
            "transitiontime": {
              "name": "Transition Time", 
              "odmRef": "#/odmData/TransitionTimeData"
            }
          }
        }, 
        "Move": {
          "name": "Move", 
          "odmRequired": [
            "#/odmObject/Level/odmAction/Move/odmData/movemode", 
            "#/odmObject/Level/odmAction/Move/odmData/rate"
          ],
          "odmInputData": [
            "#/odmObject/Level/odmAction/Move/odmData/movemode", 
            "#/odmObject/Level/odmAction/Move/odmData/rate"
          ],
          "odmData": {
            "movemode": {
              "name": "Move mode", 
              "type": "number", 
              "widthInBits": 8, 
              "enum": [
                { "up": 0 }, 
                { "down": 1 }
             ]
            }, 
            "rate": {
              "name": "Move rate", 
              "type": "number", 
              "widthInBits": 8, 
              "minimum": 0, 
              "maximum": 255
            }
          }
        }, 
        "Step": {
          "name": "Step", 
          "odmRequired": [
            "#/odmObject/Level/odmAction/Step/odmData/stepmode",
            "#/odmObject/Level/odmAction/Step/odmData/stepsize",
            "#/odmObject/Level/odmAction/Step/odmData/transitiontime"
          ],
          "odmInputData": [
            "#/odmObject/Level/odmAction/Step/odmData/stepmode",
            "#/odmObject/Level/odmAction/Step/odmData/stepsize",
            "#/odmObject/Level/odmAction/Step/odmData/transitiontime"
          ],
          "odmData": {
            "stepmode": {
              "name": "Step mode", 
              "type": "number", 
              "widthInBits": 8, 
              "enum": [
                { "up": 0 }, 
                { "down": 1 }
              ]
            }, 
            "stepsize": {
              "name": "Step size", 
              "type": "number", 
              "widthInBits": 8, 
              "minimum": 0, 
              "maximum": 255
            }, 
            "transitiontime": {
              "name": "Step Transition Time", 
              "odmRef": "#/odmData/TransitionTimeData"
            }
          }
        }, 
        "Stop": {
          "name": "Stop"
        }, 
        "MoveToLevelwithOnOff": {
          "odmRef": "#/odmObject/Level/odmAction/MoveToLevel", 
          "name": "Move To Level with On/Off"
        }, 
        "MovewithOnOff": {
          "odmRef": "#/odmObject/Level/odmAction/Move", 
          "name": "Move with On/Off"
        }, 
        "StepwithOnOff": {
          "odmRef": "#/odmObject/Level/odmAction/Step", 
          "name": "Step with On/Off"
        }, 
        "StopwithOnOff": {
          "odmRef": "#/odmObject/Level/odmAction/Stop", 
          "name": "Stop with On/Off"
        }
      }, 
      "odmData": {
        "TransitionTimeData": {
          "type": "number", 
          "widthInBits": 16, 
          "minimum": 0, 
          "maximum": 65535, 
          "multipleOf": 1, 
          "scaleUnit": "seconds", 
          "scaleMinimum": 0, 
          "scaleMaximum": 6553.5
        }
      }
    }
  }
}
