{
  "info": {
    "title": "OMA LwM2M Magnetometer (Object ID 3314)",
    "version": "20200528",
    "copyright": "Copyright (c) 2018-2020 IPSO",
    "license": "https://github.com/one-data-model/oneDM/blob/master/LICENSE"
  },
  "odmObject": {
    "Magnetometer": {
      "label": "Magnetometer",
      "description": "This IPSO object can be used to represent a 1-3 axis magnetometer with optional compass direction.",
      "odmProperty": {
        "X_Value": {
          "odmRef": "#/odmProperty/X_Value"
        },
        "Y_Value": {
          "odmRef": "#/odmProperty/Y_Value"
        },
        "Z_Value": {
          "odmRef": "#/odmProperty/Z_Value"
        },
        "Compass_Direction": {
          "odmRef": "#/odmProperty/Compass_Direction"
        },
        "Sensor_Units": {
          "odmRef": "#/odmProperty/Sensor_Units"
        }
      },
      "odmAction": {},
      "odmRequired": [
        "#/odmProperty/X_Value"
      ]
    }
  },
  "odmProperty": {
    "X_Value": {
      "label": "X Value",
      "description": "The measured value along the X axis.",
      "writable": false,
      "type": "number"
    },
    "Y_Value": {
      "label": "Y Value",
      "description": "The measured value along the Y axis.",
      "writable": false,
      "type": "number"
    },
    "Z_Value": {
      "label": "Z Value",
      "description": "The measured value along the Z axis.",
      "writable": false,
      "type": "number"
    },
    "Compass_Direction": {
      "label": "Compass Direction",
      "description": "The measured compass direction.",
      "writable": false,
      "type": "number",
      "units": "deg",
      "minimum": 0,
      "maximum": 360
    },
    "Sensor_Units": {
      "label": "Sensor Units",
      "description": "Measurement Units Definition.",
      "writable": false,
      "type": "string"
    }
  },
  "odmAction": {}
}